CHANGELOG
COPYRIGHT
INSTALL
LICENSE
MANIFEST.in
README
TODO
account_check_ar.xml
account_voucher_ar.xml
journal.xml
setup.py
tryton.cfg
./__init__.py
./account_check_ar.py
./account_check_ar.xml
./account_voucher_ar.py
./account_voucher_ar.xml
./journal.xml
./tryton.cfg
./locale/es_AR.po
./tests/__init__.py
./tests/test_account_check_ar.py
./view/account_issued_check_form.xml
./view/account_issued_check_tree.xml
./view/account_third_check_form.xml
./view/account_third_check_tree.xml
./view/issued_check_debit.xml
./view/issued_check_tree.xml
./view/journal_check_form.xml
./view/third_check_deposit.xml
./view/third_check_held.xml
./view/third_check_tree.xml
./view/third_pay_checks_tree.xml
./view/voucher_check_form.xml
locale/es_AR.po
trytonar_account_check_ar.egg-info/PKG-INFO
trytonar_account_check_ar.egg-info/SOURCES.txt
trytonar_account_check_ar.egg-info/dependency_links.txt
trytonar_account_check_ar.egg-info/entry_points.txt
trytonar_account_check_ar.egg-info/not-zip-safe
trytonar_account_check_ar.egg-info/requires.txt
trytonar_account_check_ar.egg-info/top_level.txt
view/account_issued_check_form.xml
view/account_issued_check_tree.xml
view/account_third_check_form.xml
view/account_third_check_tree.xml
view/issued_check_debit.xml
view/issued_check_tree.xml
view/journal_check_form.xml
view/third_check_deposit.xml
view/third_check_held.xml
view/third_check_tree.xml
view/third_pay_checks_tree.xml
view/voucher_check_form.xml